notte_pools/__init__.py
notte_pools/base.py
notte_pools/cdp_pool.py
notte_pools/local_pool.py
notte_pools/ports.py
notte_pools/py.typed
notte_pools-1.4.1.dist-info/METADATA
notte_pools-1.4.1.dist-info/WHEEL
notte_pools-1.4.1.dist-info/RECORD
