Metadata-Version: 2.4
Name: notte-pools
Version: 1.4.1
Summary: The pools for Notte
Author-email: Notte Team  <hello@notte.cc>
Requires-Python: >=3.11
Requires-Dist: browser-use>=0.1.40
Requires-Dist: browserbase>=1.2.0
Requires-Dist: camoufox[geoip]>=0.4.11
Requires-Dist: discord-py<2.5.0,>=2.3.0
Requires-Dist: fastapi>=0.115.8
Requires-Dist: hvac>=2.3.0
Requires-Dist: langchain-google-genai>=2.1.1
Requires-Dist: proxy-lite
Requires-Dist: slack-sdk>=3.34.0
Requires-Dist: uvicorn>=0.29.0
